for_loop_table/__init__.py
for_loop_table/add.py
for_loop_table/check.py
for_loop_table-0.0.1.dist-info/LICENSE
for_loop_table-0.0.1.dist-info/METADATA
for_loop_table-0.0.1.dist-info/WHEEL
for_loop_table-0.0.1.dist-info/top_level.txt
for_loop_table-0.0.1.dist-info/RECORD
